[
  {
    "id": 1731150138547,
    "carModel": "ferrari",
    "carReleaseDate": "2020",
    "carColor": "red"
  },
  {
    "id": 1731150139271,
    "carModel": "ferrari",
    "carReleaseDate": "2020",
    "carColor": "red"
  },
  {
    "id": 1731150139662,
    "carModel": "ferrari",
    "carReleaseDate": "2020",
    "carColor": "red"
  },
  {
    "id": 1731150140352,
    "carModel": "ferrari",
    "carReleaseDate": "2020",
    "carColor": "red"
  },
  {
    "id": 1731150141383,
    "carModel": "ferrari",
    "carReleaseDate": "2020",
    "carColor": "red"
  }
]